dktasklib/__init__.py
dktasklib/_version.py
dktasklib/clean.py
dktasklib/commands.py
dktasklib/concat.py
dktasklib/docs.py
dktasklib/environment.py
dktasklib/executables.py
dktasklib/help.py
dktasklib/jstools.py
dktasklib/lessc.py
dktasklib/manage.py
dktasklib/npm.py
dktasklib/pset.py
dktasklib/publish.py
dktasklib/rule.py
dktasklib/runners.py
dktasklib/upversion.py
dktasklib/urlinliner.py
dktasklib/utils.py
dktasklib/version.py
dktasklib/watch.py
dktasklib/wintask.py
dktasklib/entry_points/__init__.py
dktasklib/entry_points/confbase.py
dktasklib/entry_points/dktasklibcmd.py
dktasklib/entry_points/pytemplate.py
dktasklib/entry_points/taskbase.py
dktasklib/package/__init__.py
dktasklib/package/package_interface.py
dk_tasklib-3.0.6.dist-info/METADATA
dk_tasklib-3.0.6.dist-info/WHEEL
dk_tasklib-3.0.6.dist-info/entry_points.txt
dk_tasklib-3.0.6.dist-info/top_level.txt
dk_tasklib-3.0.6.dist-info/RECORD
