Metadata-Version: 2.1
Name: dk-tasklib
Version: 3.0.6
Summary: dk-tasklib - pyinvoke task library
Home-page: https://github.com/datakortet/dk-tasklib
Author: Bjorn Pettersen
Author-email: bp@datakortet.no
License: UNKNOWN
Platform: UNKNOWN
Classifier: Development Status :: 3 - Alpha
Classifier: Intended Audience :: Developers
Classifier: Programming Language :: Python
Classifier: Programming Language :: Python :: 2
Classifier: Programming Language :: Python :: 2.7
Classifier: Programming Language :: Python :: 3
Classifier: Programming Language :: Python :: 3.5
Classifier: Topic :: Software Development :: Libraries
Requires-Dist: invoke
Requires-Dist: PyYAML
Requires-Dist: dkfileutils (>=1.4.2)
Requires-Dist: pathtools
Requires-Dist: yamldirs (>=1.1.8)
